realerikrani/project/__init__.py
realerikrani/project/app.py
realerikrani/project/bearer_extractor.py
realerikrani/project/blueprint.py
realerikrani/project/db.py
realerikrani/project/error.py
realerikrani/project/model.py
realerikrani/project/payload_converter.py
realerikrani/project/py.typed
realerikrani/project/repo.py
realerikrani/project/service.py
realerikrani_project-1.0.4.dist-info/licenses/LICENSE-Apache-2.0
realerikrani_project-1.0.4.dist-info/licenses/LICENSE-BSD-3-Clause-flask
realerikrani_project-1.0.4.dist-info/licenses/LICENSE-MIT-pyjwt
realerikrani_project-1.0.4.dist-info/licenses/NOTICE
realerikrani_project-1.0.4.dist-info/METADATA
realerikrani_project-1.0.4.dist-info/WHEEL
realerikrani_project-1.0.4.dist-info/top_level.txt
realerikrani_project-1.0.4.dist-info/RECORD
