Metadata-Version: 2.4
Name: realerikrani-project
Version: 1.0.4
Summary: Add key-based project management API endpoints to your flask app.
License-Expression: Apache-2.0
Project-URL: Repository, https://github.com/realerikrani/project
Requires-Python: >=3.12
License-File: LICENSE-Apache-2.0
License-File: LICENSE-BSD-3-Clause-flask
License-File: LICENSE-MIT-pyjwt
License-File: NOTICE
Requires-Dist: flask==3.*
Requires-Dist: pyjwt[crypto]==2.*
Requires-Dist: realerikrani-sopenqlite==1.*
Requires-Dist: realerikrani-flaskapierr==1.*
Requires-Dist: realerikrani-base64token==1.*
Dynamic: license-file
